README.md
setup.cfg
setup.py
distributions/Binomialdistribution.py
distributions/Gaussiandistribution.py
distributions/Generaldistribution.py
distributions/__init__.py
jah_distribution_2020_12_28.egg-info/PKG-INFO
jah_distribution_2020_12_28.egg-info/SOURCES.txt
jah_distribution_2020_12_28.egg-info/dependency_links.txt
jah_distribution_2020_12_28.egg-info/not-zip-safe
jah_distribution_2020_12_28.egg-info/top_level.txt